nlevoshell/__init__.py
nlevoshell/connections/__init__.py
nlevoshell/connections/connections.py
nlevoshell/connections/redis.py
nlevoshell/core/__init__.py
nlevoshell/core/config.py
nlevoshell/core/core_consumer.py
nlevoshell/core/generator/__init__.py
nlevoshell/core/generator/message_generator.py
nlevoshell/core/process_controller.py
nlevoshell/core/rabbitmq/__init__.py
nlevoshell/core/rabbitmq/rabbitmq_consumer.py
nlevoshell/core/rabbitmq/rabbitmq_producer.py
nlevoshell/core/rabbitmq/rabbitmq_utils.py
nlevoshell/log_service/__init__.py
nlevoshell/log_service/adb_log/__init__.py
nlevoshell/log_service/adb_log/log_manager.py
nlevoshell/log_service/adb_log/parse.py
nlevoshell/log_service/device_command_handler.py
nlevoshell/log_service/logcollector_controller.py
nlevoshell/loop.py
nlevoshell/main.py
nlevoshell/test.py
nlevoshell/util/__init__.py
nlevoshell/util/common.py
nlevoshell-0.0.8.dist-info/LICENSE.txt
nlevoshell-0.0.8.dist-info/METADATA
nlevoshell-0.0.8.dist-info/WHEEL
nlevoshell-0.0.8.dist-info/RECORD
