Metadata-Version: 2.1
Name: nlevoshell
Version: 0.0.8
Summary: Shell module for evo.C
Author: minmax
Author-email: minmax@nextlab.co.kr
Requires-Python: >=3.10,<4.0
Classifier: Programming Language :: Python :: 3
Classifier: Programming Language :: Python :: 3.10
Classifier: Programming Language :: Python :: 3.11
Classifier: Programming Language :: Python :: 3.12
Requires-Dist: Pillow (>=10.1.0,<11.0.0)
Requires-Dist: adbutils (==2.8.0)
Requires-Dist: clickhouse-connect (>=0.8.1,<0.9.0)
Requires-Dist: iterators (>=0.2.0,<0.3.0)
Requires-Dist: joblib (==1.4.2)
Requires-Dist: kombu (>=5.4.2,<6.0.0)
Requires-Dist: nlevo (>=0.0.14,<0.0.15)
Requires-Dist: numpy (==1.26.4)
Requires-Dist: paramiko (==3.4.1)
Requires-Dist: pika (>=1.3.2,<2.0.0)
Requires-Dist: pure-python-adb (==0.3.0.dev0)
Requires-Dist: pydantic (==1.10.15)
Requires-Dist: redis (>=5.1.0,<6.0.0)
Requires-Dist: retry (>=0.9.2,<0.10.0)
